lc4/__init__.py
lc4/__main__.py
lc4/lc4.py
lc4/version.txt
lc4-0.3.0.dist-info/LICENSE
lc4-0.3.0.dist-info/METADATA
lc4-0.3.0.dist-info/WHEEL
lc4-0.3.0.dist-info/entry_points.txt
lc4-0.3.0.dist-info/top_level.txt
lc4-0.3.0.dist-info/RECORD
