Metadata-Version: 2.1
Name: lc4
Version: 0.3.0
Summary: A Python implementation of ElsieFour (LC4)
Home-page: https://github.com/dstein64/lc4
Author: Daniel Steinberg
Author-email: ds@dannyadam.com
License: MIT
Keywords: cryptography,lc4,elsie-four
Platform: UNKNOWN
Classifier: Development Status :: 4 - Beta
Classifier: Intended Audience :: Developers
Classifier: Intended Audience :: Science/Research
Classifier: Topic :: Scientific/Engineering
Classifier: Topic :: Security
Classifier: Topic :: Security :: Cryptography
Classifier: License :: OSI Approved :: MIT License
Classifier: Operating System :: Unix
Classifier: Operating System :: POSIX :: Linux
Classifier: Operating System :: MacOS
Classifier: Operating System :: Microsoft :: Windows
Classifier: Programming Language :: Python :: 3
Requires-Python: >=3.5
Requires-Dist: numpy
